MANIFEST.in
README.md
requirements.txt
setup.py
ripe_proposal_2018_06/__init__.py
ripe_proposal_2018_06/ripe_proposal_2018_06.py
ripe_proposal_2018_06/rpkitools.py
ripe_proposal_2018_06.egg-info/PKG-INFO
ripe_proposal_2018_06.egg-info/SOURCES.txt
ripe_proposal_2018_06.egg-info/dependency_links.txt
ripe_proposal_2018_06.egg-info/entry_points.txt
ripe_proposal_2018_06.egg-info/requires.txt
ripe_proposal_2018_06.egg-info/top_level.txt