Metadata-Version: 1.2
Name: ripe-proposal-2018-06
Version: 1.0.4
Summary: RIPE Policy Proposal 2018-06 Analyser
Home-page: https://github.com/job/ripe-proposal-2018-06
Maintainer: Job Snijders
Maintainer-email: job@ntt.net
License: BSD 2-Clause
Keywords: rpki prefix routing networking
Platform: UNKNOWN
Classifier: Intended Audience :: Developers
Classifier: Topic :: Software Development :: Libraries :: Python Modules
Classifier: Topic :: System :: Networking
Classifier: License :: OSI Approved :: BSD License
Classifier: Programming Language :: Python :: 3 :: Only
